go.py
stuff.py
Python_Wars_Solo-3.0.0.dist-info/LICENSE.txt
Python_Wars_Solo-3.0.0.dist-info/METADATA
Python_Wars_Solo-3.0.0.dist-info/WHEEL
Python_Wars_Solo-3.0.0.dist-info/entry_points.txt
Python_Wars_Solo-3.0.0.dist-info/top_level.txt
Python_Wars_Solo-3.0.0.dist-info/RECORD
