Metadata-Version: 2.1
Name: Python-Wars-Solo
Version: 3.0.0
Summary: A retro-style Apple ][ Basic game cooked up in 45 minutes.
Author-email: Daniel Roy Greenfeld <pydanny@gmail.com>
License: Python Wars Solo
Project-URL: Homepage, https://github.com/pydanny/Python-Wars-Solo
Project-URL: documentation, https://github.com/pydanny/Python-Wars-Solo#readme
Project-URL: changelog, https://github.com/jupyter/jupyter_events/blob/main/CHANGELOG.md
Classifier: Development Status :: 6 - Mature
Classifier: Intended Audience :: Developers
Classifier: License :: OSI Approved :: GNU General Public License (GPL)
Classifier: Natural Language :: English
Classifier: Programming Language :: Python :: 3.5
Classifier: Programming Language :: Python :: 3.6
Classifier: Programming Language :: Python
Requires-Python: >=3.8
License-File: LICENSE.txt
